{
  "apps":[
    {
      "appName":"raceCountdown",
      "placement":{
        "height":"160px",
        "left":"0px",
        "margin":"auto",
        "right":"0px",
        "top":"220px",
        "width":"690px"
      }
    },
    {
      "appName":"radialmenu",
      "placement":{
        "bottom":0,
        "height":"400px",
        "left":0,
        "margin":"auto",
        "position":"absolute",
        "right":0,
        "top":0,
        "width":"400px"
      }
    }
  ],
  "description":"layout used in 1st person",
  "title":"1st person",
  "type":"unicycle",
  "version":0.47
}